{"url": "https://www.zomato.com/pune/umesh-tamang-momos-salunkhe-vihar-road", "basic-info": {"res_id": 20030698, "name": "Umesh Tamang Momos", "cuisine_string": "Momos", "rating": {"has_fake_reviews": 0, "aggregate_rating": 0, "rating_text": "NEW", "rating_subtitle": "Not rated", "rating_color": "CBCBCB", "votes": "0", "subtext": "REVIEW", "is_new": true}, "rating_new": {"newlyOpenedObj": {"text": "Newly Opened", "color": "#FFFFFF", "bgColor": "#F4A266", "bgColorV2": {"type": "green", "tint": "100"}, "subtitle": "OUTLET", "ratingV2": "New"}, "suspiciousReviewObj": null, "ratings": []}, "res_status_text": "Open now", "timing": {"timing_desc": "5pm \u2013 11pm (Today)", "customised_timings": {"opening_hours": [{"timing": "5pm \u2013 11pm", "days": "Mon-Wed, Fri-Sun"}, {"timing": "4pm \u2013 11pm", "days": "Thu"}]}, "show_open_now": false, "show_timing_info": false}, "is_delivery_only": true, "is_perm_closed": false, "is_temp_closed": false, "is_opening_soon": 0, "should_ban_ugc": false, "is_shelled": false, "media_alert": 0, "learn_more_text": "Learn More", "res_thumb": "https://b.zmtcdn.com/images/res_avatar_476_320_1x_new.png?output-format=webp", "disclaimer_text": "", "resUrl": "/pune/umesh-tamang-momos-salunkhe-vihar-road", "is_partner": false}, "details": {"KNOWN_FOR": [], "CUISINES": {"title": "Cuisines", "cuisines": [{"deeplink": "zomato://search?deeplink_filters=WyJ7XCJjb250ZXh0XCI6XCJhbGxcIn0iLCJ7XCJjdWlzaW5lX2lkXCI6W1wiMTA1MVwiXX0iXQ%3D%3D", "url": "https://www.zomato.com/pune/restaurants/momos/", "name": "Momos"}]}, "LOCALITY": [], "IMAGE_MENUS": {"title": "Menu", "menus": [{"label": "Menu", "subtitle": "1 page", "thumb": "https://b.zmtcdn.com/data/menus/698/20030698/78b1666f6ffb5c1bb4181a1391508921.jpg?fit=around%7C200%3A200&crop=200%3A200%3B%2A%2C%2A"}]}, "PEOPLE_LIKED": [], "TOP_DISHES": [], "CFT_DETAILS": {"title": "Average Cost", "cfts": [{"title": "\u20b9100 for one order (approx.)", "subtitle": "Exclusive of applicable taxes and charges, if any"}]}, "HIGHLIGHTS": {"title": "More Info", "highlights": [{"type": "AVAILABLE", "text": "Delivery Only"}, {"type": "UNAVAILABLE", "text": "No Seating Available"}]}, "FIRE_SAFETY": [], "CHEF_DETAILS": [], "MAGIC_CELLS": []}, "contact": {"city_id": 5, "city_name": "Pune", "country_id": 1, "country_name": "India", "zipcode": "411048", "is_dark_kitchen": false, "locality_verbose": "Salunkhe Vihar Road, Pune", "latitude": "18.4785151732", "longitude": "73.8963925838", "static_map_url": "https://maps.zomato.com/php/staticmap?center=18.4785151732,73.8963925838&maptype=zomato&markers=18.4785151732,73.8963925838,pin_res32&sensor=false&scale=2&zoom=16&language=en&size=240x150&size=400x240", "address": "Shop 18/5/1, Dhanmohini Apartment, Lane 20, Salunkhe Vihar Road, Pune", "is_phone_available": 1, "phoneDetails": {"title": "Phone Numbers", "phoneStr": "+919764602425"}, "res_chain_text": "", "res_group_text": "", "res_chain_url": "", "res_group_url": "", "show_res_map": true}}